imktk/README.md
imktk/__init__.py
imktk/constants/__init__.py
imktk/constants/_constants.py
imktk/constants/_custom_defined.py
imktk/dataarray_methods/.gitinclude
imktk/dataarray_methods/_template.py
imktk/dataarray_methods/ad_temp.py
imktk/dataarray_methods/anomalies.py
imktk/dataarray_methods/climatology.py
imktk/dataarray_methods/flight_track.py
imktk/dataarray_methods/num_den.py
imktk/dataarray_methods/vapour_pres_ice.py
imktk/dataarray_methods/vapour_pres_liq.py
imktk/dataset_methods/.gitinclude
imktk/dataset_methods/_template.py
imktk/toolkit.py
imktk/tutorial.py
imktk-0.3.1.dist-info/METADATA
imktk-0.3.1.dist-info/entry_points.txt
imktk-0.3.1.dist-info/LICENSE
imktk-0.3.1.dist-info/WHEEL
imktk-0.3.1.dist-info/RECORD
